stringindexsplit/README.MD
stringindexsplit/__init__.py
stringindexsplit/requirements.txt
stringindexsplit/thirdparty.json
stringindexsplit-0.10.dist-info/LICENSE.rst
stringindexsplit-0.10.dist-info/METADATA
stringindexsplit-0.10.dist-info/WHEEL
stringindexsplit-0.10.dist-info/top_level.txt
stringindexsplit-0.10.dist-info/RECORD
