Metadata-Version: 2.1
Name: stringindexsplit
Version: 0.10
Summary: simplifies the process of splitting a list of strings at specified character indices
Home-page: https://github.com/hansalemaos/stringindexsplit
Author: Johannes Fischer
Author-email: aulasparticularesdealemaosp@gmail.com
License: MIT
Keywords: string,split
Classifier: Development Status :: 4 - Beta
Classifier: Programming Language :: Python :: 3 :: Only
Classifier: Programming Language :: Python :: 3.10
Classifier: Topic :: Software Development :: Libraries :: Python Modules
Classifier: Topic :: Utilities
License-File: LICENSE.rst
Requires-Dist: numpy
